LICENSE.md
MANIFEST.in
README.rst
pyproject.toml
requirements.core.txt
requirements.txt
setup.py
core_parser_app/__init__.py
core_parser_app/access_control.py
core_parser_app/admin.py
core_parser_app/apps.py
core_parser_app/settings.py
core_parser_app/tasks.py
core_parser_app/urls.py
core_parser_app.egg-info/PKG-INFO
core_parser_app.egg-info/SOURCES.txt
core_parser_app.egg-info/dependency_links.txt
core_parser_app.egg-info/requires.txt
core_parser_app.egg-info/top_level.txt
core_parser_app/components/__init__.py
core_parser_app/components/data_structure/__init__.py
core_parser_app/components/data_structure/admin_site.py
core_parser_app/components/data_structure/api.py
core_parser_app/components/data_structure/models.py
core_parser_app/components/data_structure_element/__init__.py
core_parser_app/components/data_structure_element/admin_site.py
core_parser_app/components/data_structure_element/api.py
core_parser_app/components/module/__init__.py
core_parser_app/components/module/admin_site.py
core_parser_app/components/module/api.py
core_parser_app/components/module/models.py
core_parser_app/management/__init__.py
core_parser_app/management/commands/__init__.py
core_parser_app/management/commands/loadmodules.py
core_parser_app/migrations/0001_initial.py
core_parser_app/migrations/__init__.py
core_parser_app/static/core_parser_app/common/css/modules.css
core_parser_app/static/core_parser_app/common/js/module_manager.js
core_parser_app/static/core_parser_app/common/js/module_manager.raw.js
core_parser_app/static/core_parser_app/common/xsd/annotations.xsd
core_parser_app/static/core_parser_app/common/xsd/boolean.xsd
core_parser_app/static/core_parser_app/common/xsd/date.xsd
core_parser_app/system/__init__.py
core_parser_app/system/api.py
core_parser_app/templates/core_parser_app/common/module_manager.html
core_parser_app/templates/core_parser_app/common/module_manager_box.html
core_parser_app/templates/core_parser_app/common/modules.html
core_parser_app/templates/core_parser_app/common/modals/add_module.html
core_parser_app/tools/__init__.py
core_parser_app/tools/modules/__init__.py
core_parser_app/tools/modules/discover.py
