Metadata-Version: 2.1
Name: core-parser-app
Version: 2.19.0
Summary: XSD parser tools for the curator core project
Home-page: https://github.com/usnistgov/core_parser_app
Author: NIST IT Lab
Author-email: itl_inquiries@nist.gov
License-File: LICENSE.md
